fairgrad/__init__.py
fairgrad/fairness_functions.py
fairgrad/torch/__init__.py
fairgrad/torch/cross_entropy.py
fairgrad/torch/fairness_loss.py
fairgrad-0.2.0.dist-info/LICENSE.md
fairgrad-0.2.0.dist-info/WHEEL
fairgrad-0.2.0.dist-info/METADATA
fairgrad-0.2.0.dist-info/RECORD
